pre_commit/__init__.py
pre_commit/__main__.py
pre_commit/all_languages.py
pre_commit/clientlib.py
pre_commit/color.py
pre_commit/constants.py
pre_commit/envcontext.py
pre_commit/error_handler.py
pre_commit/errors.py
pre_commit/file_lock.py
pre_commit/git.py
pre_commit/hook.py
pre_commit/lang_base.py
pre_commit/logging_handler.py
pre_commit/main.py
pre_commit/output.py
pre_commit/parse_shebang.py
pre_commit/prefix.py
pre_commit/repository.py
pre_commit/staged_files_only.py
pre_commit/store.py
pre_commit/util.py
pre_commit/xargs.py
pre_commit/yaml.py
pre_commit/yaml_rewrite.py
pre_commit/commands/__init__.py
pre_commit/commands/autoupdate.py
pre_commit/commands/clean.py
pre_commit/commands/gc.py
pre_commit/commands/hook_impl.py
pre_commit/commands/init_templatedir.py
pre_commit/commands/install_uninstall.py
pre_commit/commands/migrate_config.py
pre_commit/commands/run.py
pre_commit/commands/sample_config.py
pre_commit/commands/try_repo.py
pre_commit/commands/validate_config.py
pre_commit/commands/validate_manifest.py
pre_commit/languages/__init__.py
pre_commit/languages/conda.py
pre_commit/languages/coursier.py
pre_commit/languages/dart.py
pre_commit/languages/docker.py
pre_commit/languages/docker_image.py
pre_commit/languages/dotnet.py
pre_commit/languages/fail.py
pre_commit/languages/golang.py
pre_commit/languages/haskell.py
pre_commit/languages/julia.py
pre_commit/languages/lua.py
pre_commit/languages/node.py
pre_commit/languages/perl.py
pre_commit/languages/pygrep.py
pre_commit/languages/python.py
pre_commit/languages/r.py
pre_commit/languages/ruby.py
pre_commit/languages/rust.py
pre_commit/languages/script.py
pre_commit/languages/swift.py
pre_commit/languages/system.py
pre_commit/meta_hooks/__init__.py
pre_commit/meta_hooks/check_hooks_apply.py
pre_commit/meta_hooks/check_useless_excludes.py
pre_commit/meta_hooks/identity.py
pre_commit/resources/__init__.py
pre_commit/resources/empty_template_.npmignore
pre_commit/resources/empty_template_Cargo.toml
pre_commit_pegi18-4.0.1.dist-info/LICENSE
pre_commit_pegi18-4.0.1.dist-info/METADATA
pre_commit_pegi18-4.0.1.dist-info/WHEEL
pre_commit_pegi18-4.0.1.dist-info/entry_points.txt
pre_commit_pegi18-4.0.1.dist-info/top_level.txt
pre_commit_pegi18-4.0.1.dist-info/RECORD
