Metadata-Version: 2.1
Name: pre-commit-pegi18
Version: 4.0.1
Summary: A fork of the pre-commit framework (https://github.com/pre-commit/pre-commit) that allows modifications and non-zero return codes
Home-page: https://github.com/ethan-0l/pre-commit-pegi18
Author: ethan-0l
Author-email: ethan-0l@itsbi.fr
License: MIT
Project-URL: Original Project, https://github.com/pre-commit/pre-commit
Project-URL: Documentation, https://pre-commit.com
Classifier: License :: OSI Approved :: MIT License
Classifier: Programming Language :: Python :: 3
Classifier: Programming Language :: Python :: 3 :: Only
Classifier: Programming Language :: Python :: Implementation :: CPython
Classifier: Programming Language :: Python :: Implementation :: PyPy
Classifier: Intended Audience :: Developers
Requires-Python: >=3.9
License-File: LICENSE
Requires-Dist: cfgv>=2.0.0
Requires-Dist: identify>=1.0.0
Requires-Dist: nodeenv>=0.11.1
Requires-Dist: pyyaml>=5.1
Requires-Dist: virtualenv>=20.10.0
